synt/__init__.py
synt/code.py
synt/expr/__init__.py
synt/expr/alias.py
synt/expr/attribute.py
synt/expr/binary_op.py
synt/expr/call.py
synt/expr/closure.py
synt/expr/comprehension.py
synt/expr/condition.py
synt/expr/dict.py
synt/expr/empty.py
synt/expr/expr.py
synt/expr/fstring.py
synt/expr/list.py
synt/expr/modpath.py
synt/expr/named_expr.py
synt/expr/set.py
synt/expr/subscript.py
synt/expr/tuple.py
synt/expr/type_check.py
synt/expr/unary_op.py
synt/expr/wrapped.py
synt/file.py
synt/prelude.py
synt/py.typed
synt/stmt/__init__.py
synt/stmt/assertion.py
synt/stmt/assign.py
synt/stmt/block.py
synt/stmt/branch.py
synt/stmt/cls.py
synt/stmt/context.py
synt/stmt/decorator.py
synt/stmt/delete.py
synt/stmt/expression.py
synt/stmt/fn.py
synt/stmt/importing.py
synt/stmt/keyword.py
synt/stmt/loop.py
synt/stmt/match_case.py
synt/stmt/namespace.py
synt/stmt/raising.py
synt/stmt/returns.py
synt/stmt/stmt.py
synt/stmt/try_catch.py
synt/tokens/__init__.py
synt/tokens/ident.py
synt/tokens/keywords.py
synt/tokens/kv_pair.py
synt/tokens/lit.py
synt/ty/__init__.py
synt/ty/type_param.py
synt/type_check.py
synt-0.4.0.dist-info/LICENSE-APACHE
synt-0.4.0.dist-info/LICENSE-MIT
synt-0.4.0.dist-info/METADATA
synt-0.4.0.dist-info/WHEEL
synt-0.4.0.dist-info/RECORD
