Metadata-Version: 2.1
Name: synt
Version: 0.4.0
Summary: Write python with python.
Home-page: https://github.com/Embers-of-the-Fire/synt/
License: MIT OR Apache-2.0
Keywords: syntax,code,generator,template
Author: Embers-of-the-Fire
Author-email: stellarishs@163.com
Requires-Python: >=3.12,<4.0
Classifier: Development Status :: 3 - Alpha
Classifier: License :: Other/Proprietary License
Classifier: Programming Language :: Python :: 3
Classifier: Programming Language :: Python :: 3.12
Classifier: Programming Language :: Python :: 3 :: Only
Classifier: Programming Language :: Python :: Implementation
Classifier: Topic :: Printing
Classifier: Topic :: Software Development
Classifier: Topic :: Software Development :: Build Tools
Classifier: Topic :: Software Development :: Code Generators
Classifier: Topic :: Utilities
Classifier: Typing :: Typed
Project-URL: Documentation, https://embers-of-the-fire.github.io/synt/
Project-URL: Repository, https://github.com/Embers-of-the-Fire/synt.git
